postcodeinfo.py
postcodeinfo-0.0.2.dist-info/DESCRIPTION.rst
postcodeinfo-0.0.2.dist-info/METADATA
postcodeinfo-0.0.2.dist-info/metadata.json
postcodeinfo-0.0.2.dist-info/RECORD
postcodeinfo-0.0.2.dist-info/top_level.txt
postcodeinfo-0.0.2.dist-info/WHEEL
