Metadata-Version: 2.0
Name: postcodeinfo
Version: 0.0.2
Summary: API client for https://github.com/ministryofjustice/postcodeinfo
Home-page: https://github.com/ministryofjustice/postcodeinfo-client-python
Author: Andy Driver
Author-email: andy.driver@digital.justice.gov.uk
License: LICENSE
Keywords: python,ministryofjustice,govuk
Platform: any
Classifier: Programming Language :: Python
Classifier: Programming Language :: Python :: 2.7
Classifier: License :: OSI Approved :: MIT License
Classifier: Operating System :: OS Independent
Classifier: Development Status :: 3 - Alpha
Classifier: Environment :: Web Environment
Classifier: Intended Audience :: Developers
Classifier: Natural Language :: English
Classifier: Topic :: Internet :: WWW/HTTP
Classifier: Topic :: Software Development :: Libraries :: Python Modules
Requires-Dist: requests (>=2.7,<3)
